chaoxing/__init__.py
chaoxing/datas.py
chaoxing/utils.py
chaoxingapis-0.0.1.dist-info/LICENSE.txt
chaoxingapis-0.0.1.dist-info/METADATA
chaoxingapis-0.0.1.dist-info/WHEEL
chaoxingapis-0.0.1.dist-info/top_level.txt
chaoxingapis-0.0.1.dist-info/RECORD
